algservice/__init__.py
algservice/services/__init__.py
algservice/services/algservice/__init__.py
algservice/services/algservice/alg_service.py
algservice/services/algservice/alg_service_api.py
algservice/services/algservice/grpcutils.py
algservice/services/algservice/models.py
algservice/services/algservice/pb2utils.py
algservice/services/grpc/__init__.py
algservice/services/grpc/alg_service_pb2.py
algservice/services/grpc/alg_service_pb2.pyi
algservice/services/grpc/alg_service_pb2_grpc.py
algservice/util/__init__.py
algservice/util/exceptions.py
algservice/util/jsonencoder.py
algservice/util/syncutils.py
algservice/util/utils.py
alg_service_api_p12-1.0.5.dist-info/METADATA
alg_service_api_p12-1.0.5.dist-info/WHEEL
alg_service_api_p12-1.0.5.dist-info/top_level.txt
alg_service_api_p12-1.0.5.dist-info/RECORD
