Metadata-Version: 2.1
Name: alg-service-api-p12
Version: 1.0.5
Summary: alg service grpc api (for python3.12 )
Home-page: 
Author: L.K
Author-email: L.K@idontwant.com
Classifier: Programming Language :: Python :: 3
Classifier: Programming Language :: Python :: 3.12
Classifier: Topic :: Software Development :: Libraries :: Python Modules
Classifier: Operating System :: POSIX :: Linux
Requires-Python: >=3.12
Requires-Dist: grpcio ==1.64.1
Requires-Dist: grpcio-tools ==1.64.1
Requires-Dist: protobuf ==5.27.1
Requires-Dist: setuptools ==70.1.0
